odoo/addons/l10n_it_website_sale_fiscalcode/README.rst
odoo/addons/l10n_it_website_sale_fiscalcode/__init__.py
odoo/addons/l10n_it_website_sale_fiscalcode/__manifest__.py
odoo/addons/l10n_it_website_sale_fiscalcode/controllers/__init__.py
odoo/addons/l10n_it_website_sale_fiscalcode/controllers/main.py
odoo/addons/l10n_it_website_sale_fiscalcode/i18n/de.po
odoo/addons/l10n_it_website_sale_fiscalcode/i18n/es.po
odoo/addons/l10n_it_website_sale_fiscalcode/i18n/it.po
odoo/addons/l10n_it_website_sale_fiscalcode/i18n/l10n_it_website_sale_fiscalcode.pot
odoo/addons/l10n_it_website_sale_fiscalcode/i18n/sl.po
odoo/addons/l10n_it_website_sale_fiscalcode/readme/CONTRIBUTORS.rst
odoo/addons/l10n_it_website_sale_fiscalcode/readme/DESCRIPTION.rst
odoo/addons/l10n_it_website_sale_fiscalcode/readme/USAGE.rst
odoo/addons/l10n_it_website_sale_fiscalcode/static/description/icon.png
odoo/addons/l10n_it_website_sale_fiscalcode/static/description/index.html
odoo/addons/l10n_it_website_sale_fiscalcode/views/templates.xml
odoo14_addon_l10n_it_website_sale_fiscalcode-14.0.1.1.0.dist-info/METADATA
odoo14_addon_l10n_it_website_sale_fiscalcode-14.0.1.1.0.dist-info/WHEEL
odoo14_addon_l10n_it_website_sale_fiscalcode-14.0.1.1.0.dist-info/top_level.txt
odoo14_addon_l10n_it_website_sale_fiscalcode-14.0.1.1.0.dist-info/RECORD
