Metadata-Version: 2.1
Name: odoo14-addon-l10n-it-website-sale-fiscalcode
Version: 14.0.1.1.0
Summary: Website Sale FiscalCode
Home-page: https://github.com/OCA/l10n-italy/tree/14.0/l10n_it_website_sale_fiscalcode
Author: Agile Business Group,Odoo Community Association (OCA)
Author-email: support@odoo-community.org
License: AGPL-3
Platform: UNKNOWN
Classifier: Programming Language :: Python
Classifier: Framework :: Odoo
Classifier: Framework :: Odoo :: 14.0
Classifier: License :: OSI Approved :: GNU Affero General Public License v3
Requires-Python: >=3.6
Requires-Dist: odoo14-addon-l10n-it-fiscalcode
Requires-Dist: odoo <14.1dev,>=14.0a
